{"games":[{"_id":38,"date":"2018-09-20T20:20:00.000Z","homeTeam":"Browns","awayTeam":"Jets","week":3,"awayTeamScore":17,"bookSpread":-3,"curve":2,"homeTeamScore":21,"owlSpread":-3.5,"pickAwayTeam":false,"pickHomeTeam":false},{"_id":41,"date":"2018-09-23T13:00:00.000Z","homeTeam":"Chiefs","awayTeam":"49ers","week":3,"awayTeamScore":27,"bookSpread":-6.5,"curve":0,"homeTeamScore":38,"owlSpread":-5,"pickAwayTeam":false,"pickHomeTeam":false},{"_id":35,"date":"2018-09-23T13:00:00.000Z","homeTeam":"Falcons","awayTeam":"Saints","week":3,"awayTeamScore":43,"bookSpread":-3,"curve":0,"homeTeamScore":37,"owlSpread":-3,"pickAwayTeam":false,"pickHomeTeam":false},{"_id":36,"date":"2018-09-23T13:00:00.000Z","homeTeam":"Ravens","awayTeam":"Broncos","week":3,"awayTeamScore":14,"bookSpread":-5,"curve":0,"homeTeamScore":27,"owlSpread":-2,"pickAwayTeam":false,"pickHomeTeam":false},{"_id":37,"date":"2018-09-23T13:00:00.000Z","homeTeam":"Jaguars","awayTeam":"Titans","week":3,"awayTeamScore":9,"bookSpread":-7,"curve":0,"homeTeamScore":6,"owlSpread":-8.5,"pickAwayTeam":false,"pickHomeTeam":false},{"_id":33,"date":"2018-09-23T13:00:00.000Z","homeTeam":"Panthers","awayTeam":"Bengals","week":3,"awayTeamScore":21,"bookSpread":-3,"curve":0,"homeTeamScore":31,"owlSpread":-2,"pickAwayTeam":false,"pickHomeTeam":false},{"_id":47,"date":"2018-09-23T13:00:00.000Z","homeTeam":"Redskins","awayTeam":"Packers","week":3,"awayTeamScore":17,"bookSpread":3,"curve":0,"homeTeamScore":31,"owlSpread":-0.5,"pickAwayTeam":false,"pickHomeTeam":true},{"_id":40,"date":"2018-09-23T13:00:00.000Z","homeTeam":"Vikings","awayTeam":"Bills","week":3,"awayTeamScore":27,"bookSpread":-16.5,"curve":-1,"homeTeamScore":6,"owlSpread":-9,"pickAwayTeam":true,"pickHomeTeam":false},{"_id":46,"date":"2018-09-23T13:00:00.000Z","homeTeam":"Dolphins","awayTeam":"Raiders","week":3,"awayTeamScore":20,"bookSpread":-3,"curve":0,"homeTeamScore":28,"owlSpread":-2,"pickAwayTeam":false,"pickHomeTeam":false},{"_id":43,"date":"2018-09-23T13:00:00.000Z","homeTeam":"Eagles","awayTeam":"Colts","week":3,"awayTeamScore":16,"bookSpread":-6.5,"curve":0,"homeTeamScore":20,"owlSpread":-8,"pickAwayTeam":false,"pickHomeTeam":false},{"_id":48,"date":"2018-09-23T13:00:00.000Z","homeTeam":"Texans","awayTeam":"Giants","week":3,"awayTeamScore":27,"bookSpread":-6,"curve":0,"homeTeamScore":22,"owlSpread":-5.5,"pickAwayTeam":false,"pickHomeTeam":false},{"_id":39,"date":"2018-09-23T16:05:00.000Z","homeTeam":"Rams","awayTeam":"Chargers","week":3,"awayTeamScore":23,"bookSpread":-7,"curve":0,"homeTeamScore":35,"owlSpread":-4,"pickAwayTeam":false,"pickHomeTeam":false},{"_id":42,"date":"2018-09-23T16:25:00.000Z","homeTeam":"Cardinals","awayTeam":"Bears","week":3,"awayTeamScore":16,"bookSpread":6,"curve":0,"homeTeamScore":14,"owlSpread":2.5,"pickAwayTeam":false,"pickHomeTeam":true},{"_id":45,"date":"2018-09-23T16:25:00.000Z","homeTeam":"Seahawks","awayTeam":"Cowboys","week":3,"awayTeamScore":13,"bookSpread":-1,"curve":0,"homeTeamScore":24,"owlSpread":2,"pickAwayTeam":false,"pickHomeTeam":false},{"_id":34,"date":"2018-09-23T20:20:00.000Z","homeTeam":"Lions","awayTeam":"Patriots","week":3,"awayTeamScore":10,"bookSpread":6.5,"curve":2,"homeTeamScore":26,"owlSpread":2,"pickAwayTeam":false,"pickHomeTeam":true},{"_id":44,"date":"2018-09-24T20:15:00.000Z","homeTeam":"Buccaneers","awayTeam":"Steelers","week":3,"awayTeamScore":30,"bookSpread":1,"curve":1,"homeTeamScore":27,"owlSpread":-1,"pickAwayTeam":false,"pickHomeTeam":false}]}