{
    "games": [
        {
            "_id": 322 ,
            "date": "2020-10-08T20:20:00.000Z" ,
            "homeTeam": "Bears" ,
            "awayTeam": "Buccaneers" ,
            "week": 5 ,
            "awayTeamScore": "" ,
            "bookSpread": 5.5 ,
            "curve": 0 ,
            "homeTeamScore": "" ,
            "owlSpread": 1.5 ,
            "pickAwayTeam": false ,
            "pickHomeTeam": false
        } ,
        {
            "_id": 323 ,
            "date": "2020-10-11T13:00:00.000Z" ,
            "homeTeam": "Falcons" ,
            "awayTeam": "Panthers" ,
            "week": 5 ,
            "awayTeamScore": "" ,
            "bookSpread": -3.5 ,
            "curve": 0 ,
            "homeTeamScore": "" ,
            "owlSpread": -1.5 ,
            "pickAwayTeam": false ,
            "pickHomeTeam": false
        } ,
        {
            "_id": 324 ,
            "date": "2020-10-11T13:00:00.000Z" ,
            "homeTeam": "Texans" ,
            "awayTeam": "Jaguars" ,
            "week": 5 ,
            "awayTeamScore": "" ,
            "bookSpread": -6.5 ,
            "curve": 0 ,
            "homeTeamScore": "" ,
            "owlSpread": -5 ,
            "pickAwayTeam": false ,
            "pickHomeTeam": true
        } ,
        {
            "_id": 325 ,
            "date": "2020-10-11T13:00:00.000Z" ,
            "homeTeam": "Chiefs" ,
            "awayTeam": "Raiders" ,
            "week": 5 ,
            "awayTeamScore": "" ,
            "bookSpread": -12 ,
            "curve": 0 ,
            "homeTeamScore": "" ,
            "owlSpread": -11 ,
            "pickAwayTeam": false ,
            "pickHomeTeam": true
        } ,
        {
            "_id": 326 ,
            "date": "2020-10-11T13:00:00.000Z" ,
            "homeTeam": "Patriots" ,
            "awayTeam": "Broncos" ,
            "week": 5 ,
            "awayTeamScore": "" ,
            "bookSpread": -8.5 ,
            "curve": 0 ,
            "homeTeamScore": "" ,
            "owlSpread": -7.5 ,
            "pickAwayTeam": false ,
            "pickHomeTeam": true
        } ,
        {
            "_id": 327 ,
            "date": "2020-10-11T13:00:00.000Z" ,
            "homeTeam": "Jets" ,
            "awayTeam": "Cardinals" ,
            "week": 5 ,
            "awayTeamScore": "" ,
            "bookSpread": 6.5 ,
            "curve": 0 ,
            "homeTeamScore": "" ,
            "owlSpread": 4.5 ,
            "pickAwayTeam": true ,
            "pickHomeTeam": false
        } ,
        {
            "_id": 328 ,
            "date": "2020-10-11T13:00:00.000Z" ,
            "homeTeam": "Titans" ,
            "awayTeam": "Bills" ,
            "week": 5 ,
            "awayTeamScore": "" ,
            "bookSpread": 1 ,
            "curve": 0 ,
            "homeTeamScore": "" ,
            "owlSpread": 0 ,
            "pickAwayTeam": false ,
            "pickHomeTeam": false
        } ,
        {
            "_id": 329 ,
            "date": "2020-10-11T13:00:00.000Z" ,
            "homeTeam": "Steelers" ,
            "awayTeam": "Eagles" ,
            "week": 5 ,
            "awayTeamScore": "" ,
            "bookSpread": -7 ,
            "curve": 0 ,
            "homeTeamScore": "" ,
            "owlSpread": -5.5 ,
            "pickAwayTeam": false ,
            "pickHomeTeam": true
        } ,
        {
            "_id": 330 ,
            "date": "2020-10-11T13:00:00.000Z" ,
            "homeTeam": "Ravens" ,
            "awayTeam": "Bengals" ,
            "week": 5 ,
            "awayTeamScore": "" ,
            "bookSpread": -13.5 ,
            "curve": 0 ,
            "homeTeamScore": "" ,
            "owlSpread": -9.5 ,
            "pickAwayTeam": false ,
            "pickHomeTeam": true
        } ,
        {
            "_id": 331 ,
            "date": "2020-10-11T13:00:00.000Z" ,
            "homeTeam": "Football Team" ,
            "awayTeam": "Rams" ,
            "week": 5 ,
            "awayTeamScore": "" ,
            "bookSpread": 9 ,
            "curve": 0 ,
            "homeTeamScore": "" ,
            "owlSpread": 6 ,
            "pickAwayTeam": true ,
            "pickHomeTeam": false
        } ,
        {
            "_id": 332 ,
            "date": "2020-10-11T16:05:00.000Z" ,
            "homeTeam": "49ers" ,
            "awayTeam": "Dolphins" ,
            "week": 5 ,
            "awayTeamScore": "" ,
            "bookSpread": -8 ,
            "curve": 0 ,
            "homeTeamScore": "" ,
            "owlSpread": -7 ,
            "pickAwayTeam": false ,
            "pickHomeTeam": true
        } ,
        {
            "_id": 333 ,
            "date": "2020-10-11T16:25:00.000Z" ,
            "homeTeam": "Browns" ,
            "awayTeam": "Colts" ,
            "week": 5 ,
            "awayTeamScore": "" ,
            "bookSpread": 2.5 ,
            "curve": 0 ,
            "homeTeamScore": "" ,
            "owlSpread": 1 ,
            "pickAwayTeam": false ,
            "pickHomeTeam": false
        } ,
        {
            "_id": 334 ,
            "date": "2020-10-11T16:25:00.000Z" ,
            "homeTeam": "Cowboys" ,
            "awayTeam": "Giants" ,
            "week": 5 ,
            "awayTeamScore": "" ,
            "bookSpread": -9.5 ,
            "curve": 0 ,
            "homeTeamScore": "" ,
            "owlSpread": -8 ,
            "pickAwayTeam": false ,
            "pickHomeTeam": true
        } ,
        {
            "_id": 335 ,
            "date": "2020-10-11T20:20:00.000Z" ,
            "homeTeam": "Seahawks" ,
            "awayTeam": "Vikings" ,
            "week": 5 ,
            "awayTeamScore": "" ,
            "bookSpread": -7 ,
            "curve": 0 ,
            "homeTeamScore": "" ,
            "owlSpread": -5.5 ,
            "pickAwayTeam": false ,
            "pickHomeTeam": true
        } ,
        {
            "_id": 336 ,
            "date": "2020-10-12T20:15:00.000Z" ,
            "homeTeam": "Saints" ,
            "awayTeam": "Chargers" ,
            "week": 5 ,
            "awayTeamScore": "" ,
            "bookSpread": -7.5 ,
            "curve": 0 ,
            "homeTeamScore": "" ,
            "owlSpread": -8 ,
            "pickAwayTeam": false ,
            "pickHomeTeam": true
        }
    ]
}